odoo8_addon_l10n_br_data_account-8.0.1.0.1.99.dev3-py2.7-nspkg.pth
odoo_addons/l10n_br_data_account/__openerp__.py
odoo_addons/l10n_br_data_account/__init__.py
odoo_addons/l10n_br_data_account/README.rst
odoo_addons/l10n_br_data_account/data/l10n_br_account.cnae.csv
odoo_addons/l10n_br_data_account/data/l10n_br_account.service.type.csv
odoo_addons/l10n_br_data_account/demo/base_demo.xml
odoo_addons/l10n_br_data_account/static/description/icon.png
odoo8_addon_l10n_br_data_account-8.0.1.0.1.99.dev3.dist-info/top_level.txt
odoo8_addon_l10n_br_data_account-8.0.1.0.1.99.dev3.dist-info/WHEEL
odoo8_addon_l10n_br_data_account-8.0.1.0.1.99.dev3.dist-info/RECORD
odoo8_addon_l10n_br_data_account-8.0.1.0.1.99.dev3.dist-info/metadata.json
odoo8_addon_l10n_br_data_account-8.0.1.0.1.99.dev3.dist-info/DESCRIPTION.rst
odoo8_addon_l10n_br_data_account-8.0.1.0.1.99.dev3.dist-info/METADATA
odoo8_addon_l10n_br_data_account-8.0.1.0.1.99.dev3.dist-info/namespace_packages.txt
